README.md
setup.py
one_utils/__init__.py
one_utils/flow_eval.py
one_utils/torch_eval.py
one_utils/weight_transfer.py
one_utils.egg-info/PKG-INFO
one_utils.egg-info/SOURCES.txt
one_utils.egg-info/dependency_links.txt
one_utils.egg-info/top_level.txt